htdfsdk/__init__.py
htdfsdk/contract.py
htdfsdk/htdfsdk.py
htdfsdk/template.py
htdfsdk/utils.py
htdfsdk/ens/__init__.py
htdfsdk/ens/abis.py
htdfsdk/ens/auto.py
htdfsdk/ens/constants.py
htdfsdk/ens/contract_data.py
htdfsdk/ens/exceptions.py
htdfsdk/ens/main.py
htdfsdk/ens/utils.py
htdfsdk/web3/__init__.py
htdfsdk/web3/contract.py
htdfsdk/web3/datastructures.py
htdfsdk/web3/eth.py
htdfsdk/web3/exceptions.py
htdfsdk/web3/geth.py
htdfsdk/web3/iban.py
htdfsdk/web3/logs.py
htdfsdk/web3/main.py
htdfsdk/web3/manager.py
htdfsdk/web3/method.py
htdfsdk/web3/module.py
htdfsdk/web3/net.py
htdfsdk/web3/parity.py
htdfsdk/web3/pm.py
htdfsdk/web3/testing.py
htdfsdk/web3/types.py
htdfsdk/web3/version.py
htdfsdk/web3/_utils/__init__.py
htdfsdk/web3/_utils/abi.py
htdfsdk/web3/_utils/admin.py
htdfsdk/web3/_utils/blocks.py
htdfsdk/web3/_utils/caching.py
htdfsdk/web3/_utils/contracts.py
htdfsdk/web3/_utils/datatypes.py
htdfsdk/web3/_utils/decorators.py
htdfsdk/web3/_utils/empty.py
htdfsdk/web3/_utils/encoding.py
htdfsdk/web3/_utils/ens.py
htdfsdk/web3/_utils/events.py
htdfsdk/web3/_utils/filters.py
htdfsdk/web3/_utils/formatters.py
htdfsdk/web3/_utils/function_identifiers.py
htdfsdk/web3/_utils/http.py
htdfsdk/web3/_utils/hypothesis.py
htdfsdk/web3/_utils/math.py
htdfsdk/web3/_utils/method_formatters.py
htdfsdk/web3/_utils/miner.py
htdfsdk/web3/_utils/module.py
htdfsdk/web3/_utils/net.py
htdfsdk/web3/_utils/normalizers.py
htdfsdk/web3/_utils/personal.py
htdfsdk/web3/_utils/request.py
htdfsdk/web3/_utils/rpc_abi.py
htdfsdk/web3/_utils/threads.py
htdfsdk/web3/_utils/transactions.py
htdfsdk/web3/_utils/txpool.py
htdfsdk/web3/_utils/validation.py
htdfsdk/web3/_utils/windows.py
htdfsdk/web3/_utils/compat/__init__.py
htdfsdk/web3/_utils/compat/compat_py2.py
htdfsdk/web3/_utils/compat/compat_py3.py
htdfsdk/web3/_utils/module_testing/__init__.py
htdfsdk/web3/_utils/module_testing/emitter_contract.py
htdfsdk/web3/_utils/module_testing/eth_module.py
htdfsdk-1.0.5.dist-info/LICENSE
htdfsdk-1.0.5.dist-info/METADATA
htdfsdk-1.0.5.dist-info/WHEEL
htdfsdk-1.0.5.dist-info/top_level.txt
htdfsdk-1.0.5.dist-info/RECORD
