Metadata-Version: 2.1
Name: htdfsdk
Version: 1.0.5
Summary: htdf python sdk
Home-page: https://github.com/youngqqcn/htdfsdk
Author: youngqqcn
Author-email: youngqqcn@gmail.com
License: UNKNOWN
Keywords: htdf sdk
Platform: UNKNOWN
Classifier: Development Status :: 4 - Beta
Classifier: Intended Audience :: Developers
Classifier: Topic :: Software Development :: Code Generators
Classifier: License :: OSI Approved :: MIT License
Classifier: Programming Language :: Python :: 3
Classifier: Programming Language :: Python :: 3.6
Classifier: Programming Language :: Python :: 3.7
Classifier: Programming Language :: Python :: 3.8
Requires-Python: >=3.6
Requires-Dist: ecdsa
Requires-Dist: coincurve
Requires-Dist: bech32
Requires-Dist: requests
Requires-Dist: eth-abi (<3.0.0,>=2.0.0b6)
Requires-Dist: eth-account (<0.6.0,>=0.5.3)
Requires-Dist: eth-hash[pycryptodome] (<1.0.0,>=0.2.0)
Requires-Dist: eth-typing (<3.0.0,>=2.0.0)
Requires-Dist: eth-utils (<2.0.0,>=1.9.5)
Requires-Dist: hexbytes (<1.0.0,>=0.1.0)
Requires-Dist: ipfshttpclient (==0.7.0a1)
Requires-Dist: jsonschema (<4.0.0,>=3.2.0)
Requires-Dist: lru-dict (<2.0.0,>=1.1.6)
Requires-Dist: protobuf (<4,>=3.10.0)
Requires-Dist: requests (<3.0.0,>=2.16.0)
Requires-Dist: websockets (<9.0.0,>=8.1.0)
Requires-Dist: pypiwin32 (>=223) ; platform_system == "Windows"
Requires-Dist: typing-extensions (<4,>=3.7.4.1) ; python_version < "3.8"
